CMakeLists.txt
LICENSE
MANIFEST.in
README.md
c_speech_features.c
c_speech_features.h
c_speech_features_config.h.in
setup.cfg
setup.py
c_speech_features.egg-info/PKG-INFO
c_speech_features.egg-info/SOURCES.txt
c_speech_features.egg-info/dependency_links.txt
c_speech_features.egg-info/top_level.txt
kiss_fft130/CHANGELOG
kiss_fft130/COPYING
kiss_fft130/Makefile
kiss_fft130/README
kiss_fft130/README.simd
kiss_fft130/TIPS
kiss_fft130/_kiss_fft_guts.h
kiss_fft130/kiss_fft.c
kiss_fft130/kiss_fft.h
kiss_fft130/kissfft.hh
kiss_fft130/test/Makefile
kiss_fft130/test/benchfftw.c
kiss_fft130/test/benchkiss.c
kiss_fft130/test/compfft.py
kiss_fft130/test/doit.c
kiss_fft130/test/fastfir.py
kiss_fft130/test/fft.py
kiss_fft130/test/mk_test.py
kiss_fft130/test/pstats.c
kiss_fft130/test/pstats.h
kiss_fft130/test/tailscrap.m
kiss_fft130/test/test_real.c
kiss_fft130/test/test_vs_dft.c
kiss_fft130/test/testcpp.cc
kiss_fft130/test/testkiss.py
kiss_fft130/test/twotonetest.c
kiss_fft130/tools/Makefile
kiss_fft130/tools/fftutil.c
kiss_fft130/tools/kfc.c
kiss_fft130/tools/kfc.h
kiss_fft130/tools/kiss_fastfir.c
kiss_fft130/tools/kiss_fftnd.c
kiss_fft130/tools/kiss_fftnd.h
kiss_fft130/tools/kiss_fftndr.c
kiss_fft130/tools/kiss_fftndr.h
kiss_fft130/tools/kiss_fftr.c
kiss_fft130/tools/kiss_fftr.h
kiss_fft130/tools/psdpng.c
python/__init__.py
python/base.c
python/base.h
python/base.i
python/numpy.i
python/sigproc.c
python/sigproc.h
python/sigproc.i
python/test/test.py
python/test/test.wav