Metadata-Version: 1.0
Name: c-speech-features
Version: 0.4.7
Summary: A C re-implementation of python_speech_features
Home-page: https://gitlab.com/Cwiiis/c_speech_features
Author: Chris Lord
Author-email: chrislord.net@gmail.com
License: MIT
Platform: UNKNOWN
